graph_sd-0.3.1.dist-info/licenses/LICENSE
graphsd/__init__.py
graphsd/_version.py
graphsd/mining.py
graphsd/outlier.py
graphsd/patterns.py
graphsd/utils.py
graphsd/viz.py
graphsd/datasets/__init__.py
graphsd/datasets/_base.py
graphsd/datasets/benchmark_graph.py
graphsd/datasets/__pycache__/__init__.cpython-37.pyc
graphsd/datasets/__pycache__/__init__.cpython-38.pyc
graphsd/datasets/__pycache__/_base.cpython-37.pyc
graphsd/datasets/__pycache__/_base.cpython-38.pyc
graphsd/datasets/data/playground_a_position_data_anonymized.csv
graphsd/datasets/data/playground_a_social_data_anonymized.csv
graph_sd-0.3.1.dist-info/METADATA
graph_sd-0.3.1.dist-info/WHEEL
graph_sd-0.3.1.dist-info/top_level.txt
graph_sd-0.3.1.dist-info/RECORD
