Metadata-Version: 2.4
Name: graph-sd
Version: 0.3.1
Summary: Mining graphs with Subgroup Discovery
Author: Cláudio Rebelo de Sá
Author-email: "C. Centeio Jorge" <c.jorge@tudelft.nl>
License: BSD-3-Clause
Project-URL: Homepage, https://github.com/centeio/GraphSD
Project-URL: Download, https://github.com/centeio/GraphSD
Requires-Python: >=3.6
License-File: LICENSE
Requires-Dist: pandas
Requires-Dist: numpy
Requires-Dist: scipy
Requires-Dist: networkx
Requires-Dist: Orange3-Associate
Provides-Extra: tests
Requires-Dist: pytest; extra == "tests"
Requires-Dist: pytest-cov; extra == "tests"
Provides-Extra: docs
Requires-Dist: sphinx; extra == "docs"
Requires-Dist: sphinx-gallery; extra == "docs"
Requires-Dist: sphinx_rtd_theme; extra == "docs"
Requires-Dist: numpydoc; extra == "docs"
Requires-Dist: matplotlib; extra == "docs"
Dynamic: license-file
